LICENSE
README.md
setup.py
pyao/__init__.py
pyao/__main__.py
pyao/_abstract.py
pyao/_aointernal.c
pyao/presets.py
pyao/wave.py
pylibao.egg-info/PKG-INFO
pylibao.egg-info/SOURCES.txt
pylibao.egg-info/dependency_links.txt
pylibao.egg-info/top_level.txt
test/test01.py
test/test02.py
test/test03.py
test/test04.py
test/test05.py