Metadata-Version: 2.1
Name: pylibao
Version: 0.1.2
Summary: Python library for accessing the Libao API
Home-page: https://github.com/NCBM/pyao
Author: HivertMoZara
Author-email: worldmozara@gmail.com
License: MIT
Keywords: audio
Platform: UNKNOWN
Classifier: Development Status :: 3 - Alpha
Classifier: Intended Audience :: Developers
Classifier: License :: OSI Approved :: MIT License
Classifier: Programming Language :: Python :: 3
Classifier: Programming Language :: Python :: 3.6
Classifier: Programming Language :: Python :: 3.7
Classifier: Programming Language :: Python :: 3.8
Classifier: Programming Language :: Python :: 3.9
Classifier: Programming Language :: Python :: 3.10
License-File: LICENSE
